dag_sdk/__init__.py
dag_sdk/gripper.py
dag_sdk-0.1.0.dist-info/METADATA
dag_sdk-0.1.0.dist-info/WHEEL
dag_sdk-0.1.0.dist-info/top_level.txt
dag_sdk-0.1.0.dist-info/RECORD
